celldrl/__init__.py
celldrl/envs/CellEnv.py
celldrl/envs/__init__.py
celldrl/functions/__init__.py
celldrl/functions/celldrl.py
celldrl/functions/celldrl_functions.py
celldrl_ai-0.1.1.dist-info/licenses/LICENSE
celldrl_ai-0.1.1.dist-info/METADATA
celldrl_ai-0.1.1.dist-info/WHEEL
celldrl_ai-0.1.1.dist-info/top_level.txt
celldrl_ai-0.1.1.dist-info/RECORD
