Metadata-Version: 2.4
Name: celldrl-ai
Version: 0.1.1
Summary: AI Agent which reconstructs Intermediate paths from single-cell genomics data
Home-page: https://gitlab.com/ama.bioinfo/cell-drl
Author: Abdelrahman Mahmoud
Author-email: Abdelrahman Mahmoud <ama.bioinfo@gitlab.com>
Maintainer: Abdelrahman Mahmoud
Maintainer-email: Abdelrahman Mahmoud <ama.bioinfo@gitlab.com>, Jawad Asif <j.asif@cellrewire.com>
License: The software is provided under a modified Apache License Version 2.0.
Project-URL: Homepage, https://gitlab.com/ama.bioinfo/cell-drl
Project-URL: Repository, https://gitlab.com/ama.bioinfo/cell-drl.git
Project-URL: Issues, https://gitlab.com/ama.bioinfo/cell-drl/-/issues
Keywords: single-cell,reinforcement-learning,genomics,deep-learning
Classifier: Development Status :: 4 - Beta
Classifier: Intended Audience :: Science/Research
Classifier: License :: OSI Approved :: Apache Software License
Classifier: Operating System :: OS Independent
Classifier: Programming Language :: Python :: 3
Classifier: Programming Language :: Python :: 3.9
Classifier: Programming Language :: Python :: 3.10
Classifier: Programming Language :: Python :: 3.11
Classifier: Topic :: Scientific/Engineering :: Bio-Informatics
Requires-Python: <3.13,>=3.10
License-File: LICENSE
Requires-Dist: pyreadr
Requires-Dist: numpy
Requires-Dist: pandas
Requires-Dist: anndata
Requires-Dist: scanpy
Requires-Dist: matplotlib
Requires-Dist: seaborn
Requires-Dist: umap-learn
Requires-Dist: gymnasium
Requires-Dist: stable-baselines3[extra]
Requires-Dist: pynndescent
Requires-Dist: scikit-misc
Requires-Dist: leidenalg
Requires-Dist: torch
Requires-Dist: torchvision
Requires-Dist: torchaudio
Requires-Dist: tensorboard
Requires-Dist: jupyterlab
Requires-Dist: protobuf
Dynamic: license-file
